inspira/__init__.py
inspira/config.py
inspira/constants.py
inspira/enums.py
inspira/globals.py
inspira/inspira.py
inspira/logging.py
inspira/requests.py
inspira/responses.py
inspira/testclient.py
inspira/auth/__init__.py
inspira/auth/auth_utils.py
inspira/auth/decorators/__init__.py
inspira/auth/decorators/login_required.py
inspira/auth/mixins/__init__.py
inspira/auth/mixins/user_mixin.py
inspira/cli/__init__.py
inspira/cli/cli.py
inspira/cli/create_app.py
inspira/cli/create_controller.py
inspira/cli/generate_database_file.py
inspira/cli/generate_model_file.py
inspira/cli/generate_repository_file.py
inspira/cli/generate_service_file.py
inspira/cli/init_file.py
inspira/cli/templates/__init__.py
inspira/cli/templates/app_template.txt
inspira/cli/templates/controller_template.jinja2
inspira/cli/templates/database_template.txt
inspira/cli/templates/model_template.jinja2
inspira/cli/templates/repository_template.jinja2
inspira/cli/templates/service_template.jinja2
inspira/cli/templates/websocket_controller_template.jinja2
inspira/decorators/__init__.py
inspira/decorators/http_methods.py
inspira/decorators/path.py
inspira/decorators/websocket.py
inspira/helpers/__init__.py
inspira/helpers/error_handlers.py
inspira/helpers/error_templates.py
inspira/helpers/static_file_handler.py
inspira/middlewares/__init__.py
inspira/middlewares/cors.py
inspira/middlewares/sessions.py
inspira/middlewares/user_loader.py
inspira/migrations/__init__.py
inspira/migrations/migrations.py
inspira/migrations/utils.py
inspira/utils/__init__.py
inspira/utils/controller_parser.py
inspira/utils/dependency_resolver.py
inspira/utils/handler_invoker.py
inspira/utils/inflection.py
inspira/utils/naming.py
inspira/utils/param_converter.py
inspira/utils/secret_key.py
inspira/utils/session_utils.py
inspira/websockets/__init__.py
inspira/websockets/handle_websocket.py
inspira/websockets/websocket.py
inspira/websockets/websocket_controller_registry.py
inspira-0.17.0.dist-info/entry_points.txt
inspira-0.17.0.dist-info/LICENSE
inspira-0.17.0.dist-info/WHEEL
inspira-0.17.0.dist-info/METADATA
inspira-0.17.0.dist-info/RECORD
