Metadata-Version: 2.1
Name: inspira
Version: 0.17.0
Summary: Inspira is a lightweight framework for building asynchronous web applications.
Author-email: Hayri Cicek <hayri@inspiraframework.com>
Requires-Python: >=3.8
Classifier: Development Status :: 2 - Pre-Alpha
Classifier: Environment :: Web Environment
Classifier: Intended Audience :: Developers
Classifier: Operating System :: OS Independent
Classifier: Programming Language :: Python :: 3 :: Only
Classifier: Programming Language :: Python :: 3.10
Classifier: Programming Language :: Python :: 3.11
Classifier: Programming Language :: Python :: 3.12
Classifier: Topic :: Internet :: WWW/HTTP
Classifier: Topic :: Internet :: WWW/HTTP :: HTTP Servers
Classifier: License :: OSI Approved :: MIT License
Classifier: Topic :: Internet
Classifier: Topic :: Software Development :: Libraries :: Application Frameworks
Classifier: Topic :: Software Development :: Libraries :: Python Modules
Classifier: Topic :: Software Development :: Libraries
Classifier: Topic :: Software Development
Requires-Dist: Jinja2>=3.1.2
Requires-Dist: click>=8.1.7
Requires-Dist: uvicorn
Requires-Dist: httpx
Requires-Dist: sqlalchemy
Requires-Dist: bcrypt
Requires-Dist: inflect
Requires-Dist: sqlalchemy-utils
Requires-Dist: websockets
Requires-Dist: PyJWT
Requires-Dist: itsdangerous
Project-URL: Homepage, https://inspiraframework.com
Project-URL: Repository, https://github.com/cicekhayri/inspira
